bitfount/__init__.py
bitfount/__version__.py
bitfount/compatibility.py
bitfount/config.py
bitfount/exceptions.py
bitfount/hooks.py
bitfount/py.typed
bitfount/storage.py
bitfount/types.py
bitfount/_vendor/__init__.py
bitfount/_vendor/private_eye/__init__.py
bitfount/_vendor/private_eye/cli.py
bitfount/_vendor/private_eye/consts.py
bitfount/_vendor/private_eye/data.py
bitfount/_vendor/private_eye/exceptions.py
bitfount/_vendor/private_eye/output.py
bitfount/_vendor/private_eye/parse.py
bitfount/_vendor/private_eye/tiff_combiner.py
bitfount/_vendor/private_eye/version.py
bitfount/_vendor/private_eye/common/__init__.py
bitfount/_vendor/private_eye/common/file_stream_wrapper.py
bitfount/_vendor/private_eye/common/image_parser.py
bitfount/_vendor/private_eye/common/single_file_with_external_data_image_parser.py
bitfount/_vendor/private_eye/common/substream.py
bitfount/_vendor/private_eye/custom/__init__.py
bitfount/_vendor/private_eye/custom/custom_parser.py
bitfount/_vendor/private_eye/custom/get_jpeg_header_information.py
bitfount/_vendor/private_eye/external/__init__.py
bitfount/_vendor/private_eye/external/external_pb2.py
bitfount/_vendor/private_eye/external/external_pb2.pyi
bitfount/_vendor/private_eye/heidelberg/__init__.py
bitfount/_vendor/private_eye/heidelberg/data.py
bitfount/_vendor/private_eye/heidelberg/e2e_parser.py
bitfount/_vendor/private_eye/heidelberg/heidelberg_consts.py
bitfount/_vendor/private_eye/heidelberg/heidelberg_parser.py
bitfount/_vendor/private_eye/heidelberg/heidelberg_utils.py
bitfount/_vendor/private_eye/heidelberg/hr.py
bitfount/_vendor/private_eye/heidelberg/modality.py
bitfount/_vendor/private_eye/heidelberg/validator.py
bitfount/_vendor/private_eye/heidelberg/metadata_builder/__init__.py
bitfount/_vendor/private_eye/heidelberg/metadata_builder/abstract_data_builder.py
bitfount/_vendor/private_eye/heidelberg/metadata_builder/debug.py
bitfount/_vendor/private_eye/heidelberg/metadata_builder/exam.py
bitfount-11.0.0.dist-info/licenses/LICENSE
bitfount-11.0.0.dist-info/METADATA
bitfount-11.0.0.dist-info/WHEEL
bitfount-11.0.0.dist-info/entry_points.txt
bitfount-11.0.0.dist-info/top_level.txt
bitfount-11.0.0.dist-info/RECORD
