Metadata-Version: 2.4
Name: bitfount
Version: 11.0.0
Summary: Machine Learning and Federated Learning Library.
Home-page: https://github.com/bitfount/bitfount
Author: Bitfount
Author-email: info@bitfount.com
License: Apache License 2.0
Project-URL: Documentation, https://docs.bitfount.com/
Project-URL: Homepage, https://bitfount.com
Project-URL: Source Code, https://github.com/bitfount/bitfount/
Project-URL: Hub, https://hub.bitfount.com
Keywords: federated learning,privacy,AI,machine learning
Classifier: Development Status :: 4 - Beta
Classifier: Intended Audience :: Financial and Insurance Industry
Classifier: Intended Audience :: Healthcare Industry
Classifier: Intended Audience :: Information Technology
Classifier: Intended Audience :: Developers
Classifier: Intended Audience :: Science/Research
Classifier: Programming Language :: Python :: 3
Classifier: Programming Language :: Python :: 3.12
Classifier: Operating System :: OS Independent
Classifier: License :: OSI Approved :: Apache Software License
Classifier: Natural Language :: English
Classifier: Topic :: Scientific/Engineering :: Artificial Intelligence
Classifier: Topic :: Scientific/Engineering :: Information Analysis
Classifier: Topic :: Scientific/Engineering :: Bio-Informatics
Classifier: Topic :: Scientific/Engineering :: Medical Science Apps.
Classifier: Topic :: Scientific/Engineering :: Image Processing
Classifier: Topic :: Security :: Cryptography
Classifier: Topic :: System :: Distributed Computing
Classifier: Topic :: Software Development :: Libraries :: Python Modules
Requires-Python: >=3.12,<3.13
License-File: LICENSE
Requires-Dist: GPUtil>=1.4.0
Requires-Dist: PyYAML~=6.0
Requires-Dist: aiohttp>=3.12.14,>=3.9.5
Requires-Dist: albumentations>=1.3.1
Requires-Dist: apispec>=6.6.1
Requires-Dist: async-timeout~=4.0
Requires-Dist: attrs>=21.4.0,>=23.1.0
Requires-Dist: bleach>=3.3.0
Requires-Dist: boto3-stubs[s3]>=1.35
Requires-Dist: boto3>=1.35
Requires-Dist: certifi>=2024.07.04
Requires-Dist: click>=8.1.3
Requires-Dist: construct>=2.10.56
Requires-Dist: cryptography>=44.0.1
Requires-Dist: datadog-api-client>=2.15.0
Requires-Dist: decorator>=5.1.1
Requires-Dist: deprecated~=1.2
Requires-Dist: desert>=2022.9.22
Requires-Dist: diskcache~=5.0
Requires-Dist: docstring_parser>=0.15
Requires-Dist: envyaml>=1.10.211231
Requires-Dist: fastapi<=0.123.5,>=0.117.0
Requires-Dist: fhir.resources>=8.1.0
Requires-Dist: fhirpy>=2.0.15
Requires-Dist: filelock>=3.20.1
Requires-Dist: filetype>=1.2.0
Requires-Dist: fire>=0.5.0
Requires-Dist: fonttools>=4.60.2
Requires-Dist: fpdf2~=2.7.9
Requires-Dist: future<0.14.0
Requires-Dist: gitpython>=3.1.41
Requires-Dist: grpcio>=1.62.1
Requires-Dist: h11>=0.16.0
Requires-Dist: h5py>=3.3
Requires-Dist: httpx<0.28.0,>=0.24.1
Requires-Dist: idna>=3.7
Requires-Dist: imagecodecs-lite>=2019.12.3
Requires-Dist: imagesize>=1.2.0
Requires-Dist: intermine>=1.13.0
Requires-Dist: ipython>=8.8.0
Requires-Dist: isort>=5.13.2
Requires-Dist: jdcal>=1.4
Requires-Dist: jinja2>=3.1.6
Requires-Dist: joserfc>=1.3.5
Requires-Dist: jupyter-server>=2.7.2
Requires-Dist: jupyterlab>=4.5.1
Requires-Dist: lxml>=4.6.5
Requires-Dist: marshmallow-polyfield>=5.11
Requires-Dist: marshmallow-union>=0.1.15
Requires-Dist: marshmallow<4.0.0,>=3.19.0,>=3.26.2
Requires-Dist: matplotlib~=3.8.4
Requires-Dist: methodtools>=0.4.7
Requires-Dist: more-itertools>=7.1.0
Requires-Dist: msgpack>=1.0.5
Requires-Dist: nameparser~=1.0
Requires-Dist: natsort>=8.4.0
Requires-Dist: notebook>=7.5.1
Requires-Dist: numpy<2.0,>=1.26.4
Requires-Dist: onnx>=1.17.0
Requires-Dist: onnxruntime<1.21.0,>=1.17.0
Requires-Dist: opacus>=1.5.2
Requires-Dist: opencv-python-headless>=4.10.0.84
Requires-Dist: opendp!=0.10.0
Requires-Dist: opentelemetry-exporter-otlp-proto-grpc>=1.22.0
Requires-Dist: oracledb>=3.0.0
Requires-Dist: packaging>=23.1
Requires-Dist: pandas>=2.2.3
Requires-Dist: pandasql>=0.7.3
Requires-Dist: pillow>=11.3.0
Requires-Dist: prefect==3.4.5,>=3.1.5
Requires-Dist: protobuf<5,>=4,>=4.25.8,~=4.0
Requires-Dist: psutil>=5.9.5
Requires-Dist: psycopg[binary]>=3.2.3
Requires-Dist: pyarrow~=14.0
Requires-Dist: pydantic-settings>=2.6.1
Requires-Dist: pydantic>=2.7.2
Requires-Dist: pydash~=8.0
Requires-Dist: pydicom>=2.1,~=3.0.1
Requires-Dist: pyjwt>=2.7.0
Requires-Dist: pymssql>=2.3.0
Requires-Dist: pymysql>=1.1.1
Requires-Dist: pytest>=7.2.0
Requires-Dist: python-dateutil~=2.9
Requires-Dist: python-gdcm~=3.0.24
Requires-Dist: pytorch-lightning>=2.4.0
Requires-Dist: requests>=2.32.4
Requires-Dist: scikit-image>=0.18,>=0.21.0
Requires-Dist: scikit-learn<1.7.0,>=1.5.0
Requires-Dist: scipy>=1.10.0,>=1.10.1,>=1.6
Requires-Dist: semver>=3.0.4
Requires-Dist: smartnoise-sql>=1.0.6
Requires-Dist: sqlalchemy>=2.0.35
Requires-Dist: sqlparse>=0.5.0
Requires-Dist: sqlvalidator>=0.0.20
Requires-Dist: starlette>=0.49.1
Requires-Dist: statsmodels>=0.14.0
Requires-Dist: tabulate>=0.8.6
Requires-Dist: tensorboard>=2.13.0
Requires-Dist: text-unidecode~=1.3
Requires-Dist: tifffile>=2019.7.26
Requires-Dist: timm>=1.0.9
Requires-Dist: torch-optimizer>=0.3.0
Requires-Dist: torchio>=0.18.91
Requires-Dist: torchmetrics<1.7,>=1.4.2
Requires-Dist: torchvision~=0.21.0
Requires-Dist: torch~=2.6.0
Requires-Dist: tornado>=6.5.1
Requires-Dist: tqdm>=4.66.3
Requires-Dist: transformers>=4.52.1
Requires-Dist: types-decorator>=5.1.8.3
Requires-Dist: typing_extensions>=4.12.2
Requires-Dist: urllib3>=2.6.0
Requires-Dist: uv>=0.9.6
Requires-Dist: werkzeug>=3.1.4
Requires-Dist: zipp>=3.19.1
Requires-Dist: zstandard>=0.23.0
Provides-Extra: tests
Requires-Dist: aiohappyeyeballs==2.6.1; extra == "tests"
Requires-Dist: aiohttp==3.12.15; extra == "tests"
Requires-Dist: aiosignal==1.4.0; extra == "tests"
Requires-Dist: annotated-types==0.7.0; extra == "tests"
Requires-Dist: antlr4-python3-runtime==4.9.3; extra == "tests"
Requires-Dist: anyio==4.6.2.post1; extra == "tests"
Requires-Dist: apispec==6.7.1; extra == "tests"
Requires-Dist: appnope==0.1.4; extra == "tests"
Requires-Dist: argon2-cffi==23.1.0; extra == "tests"
Requires-Dist: argon2-cffi-bindings==21.2.0; extra == "tests"
Requires-Dist: arrow==1.3.0; extra == "tests"
Requires-Dist: asttokens==2.4.1; extra == "tests"
Requires-Dist: async-lru==2.0.4; extra == "tests"
Requires-Dist: attrs==24.2.0; extra == "tests"
Requires-Dist: aws-sam-translator==1.100.0; extra == "tests"
Requires-Dist: aws-xray-sdk==2.14.0; extra == "tests"
Requires-Dist: babel==2.16.0; extra == "tests"
Requires-Dist: beautifulsoup4==4.12.3; extra == "tests"
Requires-Dist: bleach==6.2.0; extra == "tests"
Requires-Dist: blinker==1.9.0; extra == "tests"
Requires-Dist: boto3==1.40.38; extra == "tests"
Requires-Dist: botocore==1.40.38; extra == "tests"
Requires-Dist: cachetools==5.5.0; extra == "tests"
Requires-Dist: certifi==2024.8.30; extra == "tests"
Requires-Dist: cffi==1.17.1; extra == "tests"
Requires-Dist: cfn-lint==1.40.0; extra == "tests"
Requires-Dist: chardet==5.2.0; extra == "tests"
Requires-Dist: charset-normalizer==3.4.0; extra == "tests"
Requires-Dist: click==8.1.7; extra == "tests"
Requires-Dist: colorama==0.4.6; extra == "tests"
Requires-Dist: comm==0.2.2; extra == "tests"
Requires-Dist: coverage==7.6.8; extra == "tests"
Requires-Dist: cryptography==44.0.1; extra == "tests"
Requires-Dist: debugpy==1.8.9; extra == "tests"
Requires-Dist: decorator==5.1.1; extra == "tests"
Requires-Dist: defusedxml==0.7.1; extra == "tests"
Requires-Dist: distlib==0.3.9; extra == "tests"
Requires-Dist: docker==7.1.0; extra == "tests"
Requires-Dist: docker-pycreds==0.4.0; extra == "tests"
Requires-Dist: environs==14.1.1; extra == "tests"
Requires-Dist: execnet==2.1.1; extra == "tests"
Requires-Dist: executing==2.1.0; extra == "tests"
Requires-Dist: faker==37.4.0; extra == "tests"
Requires-Dist: fastjsonschema==2.21.0; extra == "tests"
Requires-Dist: filelock==3.20.1; extra == "tests"
Requires-Dist: flask==3.1.1; extra == "tests"
Requires-Dist: flask-cors==6.0.1; extra == "tests"
Requires-Dist: fqdn==1.5.1; extra == "tests"
Requires-Dist: frozenlist==1.5.0; extra == "tests"
Requires-Dist: gitdb==4.0.11; extra == "tests"
Requires-Dist: gitpython==3.1.43; extra == "tests"
Requires-Dist: graphql-core==3.2.5; extra == "tests"
Requires-Dist: h11==0.16.0; extra == "tests"
Requires-Dist: httpcore==1.0.9; extra == "tests"
Requires-Dist: httpx==0.27.2; extra == "tests"
Requires-Dist: idna==3.10; extra == "tests"
Requires-Dist: iniconfig==2.0.0; extra == "tests"
Requires-Dist: ipykernel==6.29.5; extra == "tests"
Requires-Dist: ipynb==0.5.1; extra == "tests"
Requires-Dist: ipython==8.29.0; extra == "tests"
Requires-Dist: isoduration==20.11.0; extra == "tests"
Requires-Dist: itsdangerous==2.2.0; extra == "tests"
Requires-Dist: jedi==0.19.2; extra == "tests"
Requires-Dist: jinja2==3.1.6; extra == "tests"
Requires-Dist: jmespath==1.0.1; extra == "tests"
Requires-Dist: joserfc==1.4.3; extra == "tests"
Requires-Dist: json5==0.10.0; extra == "tests"
Requires-Dist: jsonpatch==1.33; extra == "tests"
Requires-Dist: jsonpath-ng==1.7.0; extra == "tests"
Requires-Dist: jsonpointer==3.0.0; extra == "tests"
Requires-Dist: jsonschema==4.23.0; extra == "tests"
Requires-Dist: jsonschema-path==0.3.4; extra == "tests"
Requires-Dist: jsonschema-specifications==2024.10.1; extra == "tests"
Requires-Dist: jupyter-client==8.6.3; extra == "tests"
Requires-Dist: jupyter-core==5.7.2; extra == "tests"
Requires-Dist: jupyter-events==0.10.0; extra == "tests"
Requires-Dist: jupyter-lsp==2.2.5; extra == "tests"
Requires-Dist: jupyter-server==2.14.2; extra == "tests"
Requires-Dist: jupyter-server-terminals==0.5.3; extra == "tests"
Requires-Dist: jupyterlab==4.5.1; extra == "tests"
Requires-Dist: jupyterlab-pygments==0.3.0; extra == "tests"
Requires-Dist: jupyterlab-server==2.28.0; extra == "tests"
Requires-Dist: jupytext==1.16.4; extra == "tests"
Requires-Dist: lazy-object-proxy==1.12.0; extra == "tests"
Requires-Dist: markdown-it-py==3.0.0; extra == "tests"
Requires-Dist: markupsafe==3.0.2; extra == "tests"
Requires-Dist: marshmallow==3.26.2; extra == "tests"
Requires-Dist: matplotlib-inline==0.1.7; extra == "tests"
Requires-Dist: mdit-py-plugins==0.4.2; extra == "tests"
Requires-Dist: mdurl==0.1.2; extra == "tests"
Requires-Dist: mirakuru==2.5.3; extra == "tests"
Requires-Dist: mistune==3.0.2; extra == "tests"
Requires-Dist: moto==5.1.13; extra == "tests"
Requires-Dist: mpmath==1.3.0; extra == "tests"
Requires-Dist: multidict==6.1.0; extra == "tests"
Requires-Dist: nbclient==0.10.0; extra == "tests"
Requires-Dist: nbconvert==7.16.4; extra == "tests"
Requires-Dist: nbformat==5.10.4; extra == "tests"
Requires-Dist: nest-asyncio==1.6.0; extra == "tests"
Requires-Dist: networkx==3.4.2; extra == "tests"
Requires-Dist: notebook==7.5.1; extra == "tests"
Requires-Dist: notebook-shim==0.2.4; extra == "tests"
Requires-Dist: openapi-schema-validator==0.6.3; extra == "tests"
Requires-Dist: openapi-spec-validator==0.7.2; extra == "tests"
Requires-Dist: overrides==7.7.0; extra == "tests"
Requires-Dist: packaging==24.2; extra == "tests"
Requires-Dist: pandocfilters==1.5.1; extra == "tests"
Requires-Dist: parso==0.8.4; extra == "tests"
Requires-Dist: pathable==0.4.4; extra == "tests"
Requires-Dist: pexpect==4.9.0; extra == "tests"
Requires-Dist: platformdirs==4.3.6; extra == "tests"
Requires-Dist: pluggy==1.5.0; extra == "tests"
Requires-Dist: ply==3.11; extra == "tests"
Requires-Dist: port-for==0.7.4; extra == "tests"
Requires-Dist: prometheus-client==0.21.0; extra == "tests"
Requires-Dist: prompt-toolkit==3.0.48; extra == "tests"
Requires-Dist: propcache==0.2.0; extra == "tests"
Requires-Dist: protobuf==4.25.8; extra == "tests"
Requires-Dist: psutil==6.1.0; extra == "tests"
Requires-Dist: psycopg==3.2.9; extra == "tests"
Requires-Dist: psycopg-binary==3.2.9; extra == "tests"
Requires-Dist: ptyprocess==0.7.0; extra == "tests"
Requires-Dist: pure-eval==0.2.3; extra == "tests"
Requires-Dist: py-partiql-parser==0.6.1; extra == "tests"
Requires-Dist: pycparser==2.22; extra == "tests"
Requires-Dist: pydantic==2.9.2; extra == "tests"
Requires-Dist: pydantic-core==2.23.4; extra == "tests"
Requires-Dist: pygments==2.18.0; extra == "tests"
Requires-Dist: pyparsing==3.2.0; extra == "tests"
Requires-Dist: pyproject-api==1.8.0; extra == "tests"
Requires-Dist: pytest==7.4.4; extra == "tests"
Requires-Dist: pytest-aiohttp==1.0.5; extra == "tests"
Requires-Dist: pytest-asyncio==0.23.8; extra == "tests"
Requires-Dist: pytest-cov==6.0.0; extra == "tests"
Requires-Dist: pytest-custom-exit-code==0.3.0; extra == "tests"
Requires-Dist: pytest-flakefinder==1.1.0; extra == "tests"
Requires-Dist: pytest-flask==1.3.0; extra == "tests"
Requires-Dist: pytest-httpx==0.30.0; extra == "tests"
Requires-Dist: pytest-lazy-fixture==0.6.3; extra == "tests"
Requires-Dist: pytest-mock==3.14.0; extra == "tests"
Requires-Dist: pytest-postgresql==6.1.1; extra == "tests"
Requires-Dist: pytest-randomly==3.16.0; extra == "tests"
Requires-Dist: pytest-timeout==2.3.1; extra == "tests"
Requires-Dist: pytest-xdist==3.6.1; extra == "tests"
Requires-Dist: python-dateutil==2.9.0.post0; extra == "tests"
Requires-Dist: python-dotenv==1.0.1; extra == "tests"
Requires-Dist: python-json-logger==2.0.7; extra == "tests"
Requires-Dist: pyyaml==6.0.2; extra == "tests"
Requires-Dist: pyzmq==26.2.0; extra == "tests"
Requires-Dist: referencing==0.35.1; extra == "tests"
Requires-Dist: regex==2024.11.6; extra == "tests"
Requires-Dist: requests==2.32.4; extra == "tests"
Requires-Dist: requests-toolbelt==1.0.0; extra == "tests"
Requires-Dist: responses==0.25.3; extra == "tests"
Requires-Dist: rfc3339-validator==0.1.4; extra == "tests"
Requires-Dist: rfc3986-validator==0.1.1; extra == "tests"
Requires-Dist: rpds-py==0.21.0; extra == "tests"
Requires-Dist: s3transfer==0.14.0; extra == "tests"
Requires-Dist: send2trash==1.8.3; extra == "tests"
Requires-Dist: sentry-sdk==2.19.0; extra == "tests"
Requires-Dist: setproctitle==1.3.4; extra == "tests"
Requires-Dist: six==1.16.0; extra == "tests"
Requires-Dist: smmap==5.0.1; extra == "tests"
Requires-Dist: sniffio==1.3.1; extra == "tests"
Requires-Dist: soupsieve==2.6; extra == "tests"
Requires-Dist: stack-data==0.6.3; extra == "tests"
Requires-Dist: sympy==1.13.1; extra == "tests"
Requires-Dist: terminado==0.18.1; extra == "tests"
Requires-Dist: testbook==0.4.2; extra == "tests"
Requires-Dist: testcontainers==4.12.0; extra == "tests"
Requires-Dist: tinycss2==1.4.0; extra == "tests"
Requires-Dist: tornado==6.5.1; extra == "tests"
Requires-Dist: tox==4.23.2; extra == "tests"
Requires-Dist: traitlets==5.14.3; extra == "tests"
Requires-Dist: types-python-dateutil==2.9.0.20241003; extra == "tests"
Requires-Dist: typing-extensions==4.12.2; extra == "tests"
Requires-Dist: tzdata==2024.2; extra == "tests"
Requires-Dist: uri-template==1.3.0; extra == "tests"
Requires-Dist: urllib3==2.6.0; extra == "tests"
Requires-Dist: virtualenv==20.28.0; extra == "tests"
Requires-Dist: wandb==0.18.7; extra == "tests"
Requires-Dist: wcwidth==0.2.13; extra == "tests"
Requires-Dist: webcolors==24.11.1; extra == "tests"
Requires-Dist: webencodings==0.5.1; extra == "tests"
Requires-Dist: websocket-client==1.8.0; extra == "tests"
Requires-Dist: werkzeug==3.1.4; extra == "tests"
Requires-Dist: wrapt==1.17.0; extra == "tests"
Requires-Dist: xmltodict==1.0.2; extra == "tests"
Requires-Dist: yarl==1.18.0; extra == "tests"
Provides-Extra: tutorials
Requires-Dist: anyio==4.6.2.post1; extra == "tutorials"
Requires-Dist: appnope==0.1.4; extra == "tutorials"
Requires-Dist: argon2-cffi==23.1.0; extra == "tutorials"
Requires-Dist: argon2-cffi-bindings==21.2.0; extra == "tutorials"
Requires-Dist: arrow==1.3.0; extra == "tutorials"
Requires-Dist: asttokens==2.4.1; extra == "tutorials"
Requires-Dist: async-lru==2.0.4; extra == "tutorials"
Requires-Dist: attrs==24.2.0; extra == "tutorials"
Requires-Dist: babel==2.16.0; extra == "tutorials"
Requires-Dist: beautifulsoup4==4.12.3; extra == "tutorials"
Requires-Dist: bleach==6.2.0; extra == "tutorials"
Requires-Dist: certifi==2024.8.30; extra == "tutorials"
Requires-Dist: cffi==1.17.1; extra == "tutorials"
Requires-Dist: charset-normalizer==3.4.0; extra == "tutorials"
Requires-Dist: comm==0.2.2; extra == "tutorials"
Requires-Dist: contourpy==1.3.1; extra == "tutorials"
Requires-Dist: cycler==0.12.1; extra == "tutorials"
Requires-Dist: debugpy==1.8.9; extra == "tutorials"
Requires-Dist: decorator==5.1.1; extra == "tutorials"
Requires-Dist: defusedxml==0.7.1; extra == "tutorials"
Requires-Dist: executing==2.1.0; extra == "tutorials"
Requires-Dist: fastjsonschema==2.21.0; extra == "tutorials"
Requires-Dist: fonttools==4.61.1; extra == "tutorials"
Requires-Dist: fqdn==1.5.1; extra == "tutorials"
Requires-Dist: h11==0.16.0; extra == "tutorials"
Requires-Dist: httpcore==1.0.9; extra == "tutorials"
Requires-Dist: httpx==0.27.2; extra == "tutorials"
Requires-Dist: idna==3.10; extra == "tutorials"
Requires-Dist: ipykernel==6.29.5; extra == "tutorials"
Requires-Dist: ipython==8.29.0; extra == "tutorials"
Requires-Dist: ipython-genutils==0.2.0; extra == "tutorials"
Requires-Dist: ipywidgets==8.1.5; extra == "tutorials"
Requires-Dist: isoduration==20.11.0; extra == "tutorials"
Requires-Dist: jedi==0.19.2; extra == "tutorials"
Requires-Dist: jinja2==3.1.6; extra == "tutorials"
Requires-Dist: json5==0.10.0; extra == "tutorials"
Requires-Dist: jsonpointer==3.0.0; extra == "tutorials"
Requires-Dist: jsonschema==4.23.0; extra == "tutorials"
Requires-Dist: jsonschema-specifications==2024.10.1; extra == "tutorials"
Requires-Dist: jupyter-client==8.6.3; extra == "tutorials"
Requires-Dist: jupyter-contrib-core==0.4.2; extra == "tutorials"
Requires-Dist: jupyter-contrib-nbextensions==0.7.0; extra == "tutorials"
Requires-Dist: jupyter-core==5.7.2; extra == "tutorials"
Requires-Dist: jupyter-events==0.10.0; extra == "tutorials"
Requires-Dist: jupyter-highlight-selected-word==0.2.0; extra == "tutorials"
Requires-Dist: jupyter-lsp==2.2.5; extra == "tutorials"
Requires-Dist: jupyter-nbextensions-configurator==0.6.4; extra == "tutorials"
Requires-Dist: jupyter-server==2.14.2; extra == "tutorials"
Requires-Dist: jupyter-server-terminals==0.5.3; extra == "tutorials"
Requires-Dist: jupyterlab==4.5.1; extra == "tutorials"
Requires-Dist: jupyterlab-pygments==0.3.0; extra == "tutorials"
Requires-Dist: jupyterlab-server==2.28.0; extra == "tutorials"
Requires-Dist: jupyterlab-widgets==3.0.13; extra == "tutorials"
Requires-Dist: jupytext==1.16.4; extra == "tutorials"
Requires-Dist: kiwisolver==1.4.7; extra == "tutorials"
Requires-Dist: lxml==5.3.0; extra == "tutorials"
Requires-Dist: markdown-it-py==3.0.0; extra == "tutorials"
Requires-Dist: markupsafe==3.0.2; extra == "tutorials"
Requires-Dist: matplotlib==3.8.4; extra == "tutorials"
Requires-Dist: matplotlib-inline==0.1.7; extra == "tutorials"
Requires-Dist: mdit-py-plugins==0.4.2; extra == "tutorials"
Requires-Dist: mdurl==0.1.2; extra == "tutorials"
Requires-Dist: mistune==3.0.2; extra == "tutorials"
Requires-Dist: nbclient==0.10.0; extra == "tutorials"
Requires-Dist: nbconvert==7.16.4; extra == "tutorials"
Requires-Dist: nbformat==5.10.4; extra == "tutorials"
Requires-Dist: nest-asyncio==1.6.0; extra == "tutorials"
Requires-Dist: notebook==7.5.1; extra == "tutorials"
Requires-Dist: notebook-shim==0.2.4; extra == "tutorials"
Requires-Dist: numpy==1.26.4; extra == "tutorials"
Requires-Dist: overrides==7.7.0; extra == "tutorials"
Requires-Dist: packaging==24.2; extra == "tutorials"
Requires-Dist: pandocfilters==1.5.1; extra == "tutorials"
Requires-Dist: parso==0.8.4; extra == "tutorials"
Requires-Dist: pexpect==4.9.0; extra == "tutorials"
Requires-Dist: pillow==11.3.0; extra == "tutorials"
Requires-Dist: platformdirs==4.3.6; extra == "tutorials"
Requires-Dist: prometheus-client==0.21.0; extra == "tutorials"
Requires-Dist: prompt-toolkit==3.0.48; extra == "tutorials"
Requires-Dist: psutil==6.1.0; extra == "tutorials"
Requires-Dist: ptyprocess==0.7.0; extra == "tutorials"
Requires-Dist: pure-eval==0.2.3; extra == "tutorials"
Requires-Dist: pycparser==2.22; extra == "tutorials"
Requires-Dist: pygments==2.18.0; extra == "tutorials"
Requires-Dist: pyparsing==3.2.0; extra == "tutorials"
Requires-Dist: python-dateutil==2.9.0.post0; extra == "tutorials"
Requires-Dist: python-json-logger==2.0.7; extra == "tutorials"
Requires-Dist: pyyaml==6.0.2; extra == "tutorials"
Requires-Dist: pyzmq==26.2.0; extra == "tutorials"
Requires-Dist: referencing==0.35.1; extra == "tutorials"
Requires-Dist: requests==2.32.4; extra == "tutorials"
Requires-Dist: rfc3339-validator==0.1.4; extra == "tutorials"
Requires-Dist: rfc3986-validator==0.1.1; extra == "tutorials"
Requires-Dist: rpds-py==0.21.0; extra == "tutorials"
Requires-Dist: send2trash==1.8.3; extra == "tutorials"
Requires-Dist: six==1.16.0; extra == "tutorials"
Requires-Dist: sniffio==1.3.1; extra == "tutorials"
Requires-Dist: soupsieve==2.6; extra == "tutorials"
Requires-Dist: stack-data==0.6.3; extra == "tutorials"
Requires-Dist: terminado==0.18.1; extra == "tutorials"
Requires-Dist: tinycss2==1.4.0; extra == "tutorials"
Requires-Dist: tornado==6.5.1; extra == "tutorials"
Requires-Dist: tqdm==4.67.1; extra == "tutorials"
Requires-Dist: traitlets==5.14.3; extra == "tutorials"
Requires-Dist: types-python-dateutil==2.9.0.20241003; extra == "tutorials"
Requires-Dist: uri-template==1.3.0; extra == "tutorials"
Requires-Dist: urllib3==2.6.0; extra == "tutorials"
Requires-Dist: wcwidth==0.2.13; extra == "tutorials"
Requires-Dist: webcolors==24.11.1; extra == "tutorials"
Requires-Dist: webencodings==0.5.1; extra == "tutorials"
Requires-Dist: websocket-client==1.8.0; extra == "tutorials"
Requires-Dist: widgetsnbextension==4.0.13; extra == "tutorials"
Dynamic: author
Dynamic: author-email
Dynamic: classifier
Dynamic: description
Dynamic: description-content-type
Dynamic: home-page
Dynamic: keywords
Dynamic: license
Dynamic: license-file
Dynamic: project-url
Dynamic: provides-extra
Dynamic: requires-dist
Dynamic: requires-python
Dynamic: summary
